outreachspeedoflight/__init__.py
outreachspeedoflight/daq.py
outreachspeedoflight/highscorewindow.py
outreachspeedoflight/logo01.png
outreachspeedoflight/logo02.png
outreachspeedoflight/speedoflightgui.py
outreachspeedoflight/strings.py
outreachspeedoflight_tspspi-0.0.1a22.dist-info/LICENSE.md
outreachspeedoflight_tspspi-0.0.1a22.dist-info/METADATA
outreachspeedoflight_tspspi-0.0.1a22.dist-info/WHEEL
outreachspeedoflight_tspspi-0.0.1a22.dist-info/entry_points.txt
outreachspeedoflight_tspspi-0.0.1a22.dist-info/top_level.txt
outreachspeedoflight_tspspi-0.0.1a22.dist-info/RECORD
