Metadata-Version: 2.1
Name: outreachspeedoflight-tspspi
Version: 0.0.1a22
Summary: Simple frontend to illustrate our speed of light measurements for Wiener Forschungsfest
Home-page: https://github.com/tspspi/outreachspeedoflight
Author: Thomas Spielauer
Author-email: pypipackages01@tspi.at
Classifier: Programming Language :: Python :: 3
Classifier: License :: OSI Approved :: BSD License
Classifier: Operating System :: OS Independent
Requires-Python: >=3.6
License-File: LICENSE.md
Requires-Dist: matplotlib >=3.4.3
Requires-Dist: FreeSimpleGUI >=5.1.0
Requires-Dist: numpy >=1.22.4
Requires-Dist: lmfit >=1.0.3
Requires-Dist: Pillow >=9.1.1
